[
  {
    "name": "myPTA",
    "description": "My PTA is a mobile phone application for the use of parent-teacher associations.",
    "image": "/assets/images/projects/myPta.jpg",
    "url": "https://www.mypta.co.uk/"
  },
  {
    "name": "DNS.Surf",
    "description": "Querying DNS Resolution Results in Different Regions Worldwide.",
    "image": "/assets/images/projects/dns.surf.png",
    "url": "https://dns.surf"
  },
  {
    "name": "HTML.ZONE",
    "description": "Web Toolbox.",
    "image": "/assets/images/projects/html.zone.png",
    "url": "https://html.zone"
  }
]
